[
  {
    "id": "tights",
    "name": "Tights / Strumpfhose",
    "slot": "legs",
    "fit": "base",
    "clo": 0.02,
    "waterproof": false,
    "windproof": false,
    "coverage": "full",
    "upf": 5
  },
  {
    "id": "panties_women",
    "name": "Slip (Damen)",
    "slot": "legs",
    "fit": "base",
    "clo": 0.03,
    "waterproof": false,
    "windproof": false,
    "coverage": "low",
    "upf": 5
  },
  {
    "id": "briefs_men",
    "name": "Slip / Unterhose (Herren)",
    "slot": "legs",
    "fit": "base",
    "clo": 0.04,
    "waterproof": false,
    "windproof": false,
    "coverage": "low",
    "upf": 5
  },
  {
    "id": "boxer_synthetic",
    "name": "Boxershort (Mikrofaser)",
    "slot": "legs",
    "fit": "base",
    "clo": 0.05,
    "waterproof": false,
    "windproof": false,
    "coverage": "low",
    "upf": 10
  },
  {
    "id": "boxer_mesh",
    "name": "Boxershort (Mesh)",
    "slot": "legs",
    "fit": "base",
    "clo": 0.03,
    "waterproof": false,
    "windproof": false,
    "coverage": "low",
    "upf": 5
  },
  {
    "id": "boxer_cotton",
    "name": "Boxershort (Baumwolle)",
    "slot": "legs",
    "fit": "base",
    "clo": 0.06,
    "waterproof": false,
    "windproof": false,
    "coverage": "low",
    "upf": 10
  },
  {
    "id": "long_underwear_wool",
    "name": "Unterhose halblang (Wolle)",
    "slot": "legs",
    "fit": "base",
    "clo": 0.06,
    "waterproof": false,
    "windproof": false,
    "coverage": "medium",
    "upf": 15
  },
  {
    "id": "long_johns",
    "name": "Unterhose langes Bein",
    "slot": "legs",
    "fit": "base",
    "clo": 0.10,
    "waterproof": false,
    "windproof": false,
    "coverage": "full",
    "upf": 15
  },
  {
    "id": "bra",
    "name": "BH",
    "slot": "torso",
    "fit": "base",
    "clo": 0.01,
    "waterproof": false,
    "windproof": false,
    "coverage": "low",
    "upf": 5
  },
  {
    "id": "undershirt_sleeveless",
    "name": "Unterhemd aermellos",
    "slot": "torso",
    "fit": "base",
    "clo": 0.06,
    "waterproof": false,
    "windproof": false,
    "coverage": "low",
    "upf": 10
  },
  {
    "id": "t_shirt_base",
    "name": "T-Shirt (Unterwaesche)",
    "slot": "torso",
    "fit": "base",
    "clo": 0.09,
    "waterproof": false,
    "windproof": false,
    "coverage": "medium",
    "upf": 10
  },
  {
    "id": "undershirt_longsleeve",
    "name": "Unterhemd mit langen Aermeln",
    "slot": "torso",
    "fit": "base",
    "clo": 0.12,
    "waterproof": false,
    "windproof": false,
    "coverage": "full",
    "upf": 15
  },
  {
    "id": "ski_base_layer_light",
    "name": "Ski-Unterwaesche Set (duenn)",
    "slot": "torso",
    "fit": "base",
    "clo": 0.30,
    "waterproof": false,
    "windproof": false,
    "coverage": "full",
    "upf": 30
  },
  {
    "id": "ski_base_layer_heavy",
    "name": "Ski-Unterwaesche Set (dick)",
    "slot": "torso",
    "fit": "base",
    "clo": 0.40,
    "waterproof": false,
    "windproof": false,
    "coverage": "full",
    "upf": 40
  },
  {
    "id": "tube_top",
    "name": "Tube Top",
    "slot": "torso",
    "fit": "mid",
    "clo": 0.06,
    "waterproof": false,
    "windproof": false,
    "coverage": "low",
    "upf": 10
  },
  {
    "id": "t_shirt_synthetic",
    "name": "T-Shirt (Synthetik)",
    "slot": "torso",
    "fit": "mid",
    "clo": 0.08,
    "waterproof": false,
    "windproof": false,
    "coverage": "medium",
    "upf": 15
  },
  {
    "id": "t_shirt_cotton_light",
    "name": "T-Shirt (Baumwolle duenn)",
    "slot": "torso",
    "fit": "mid",
    "clo": 0.08,
    "waterproof": false,
    "windproof": false,
    "coverage": "medium",
    "upf": 10
  },
  {
    "id": "t_shirt_cotton_heavy",
    "name": "T-Shirt (Baumwolle dick)",
    "slot": "torso",
    "fit": "mid",
    "clo": 0.10,
    "waterproof": false,
    "windproof": false,
    "coverage": "medium",
    "upf": 15
  },
  {
    "id": "shirt_short_sleeve",
    "name": "Kurzarm-Hemd",
    "slot": "torso",
    "fit": "mid",
    "clo": 0.09,
    "waterproof": false,
    "windproof": false,
    "coverage": "medium",
    "upf": 15
  },
  {
    "id": "blouse_light",
    "name": "Leichte Bluse (langarm)",
    "slot": "torso",
    "fit": "mid",
    "clo": 0.15,
    "waterproof": false,
    "windproof": false,
    "coverage": "full",
    "upf": 20
  },
  {
    "id": "shirt_light",
    "name": "Leichtes Hemd (langarm)",
    "slot": "torso",
    "fit": "mid",
    "clo": 0.20,
    "waterproof": false,
    "windproof": false,
    "coverage": "full",
    "upf": 20
  },
  {
    "id": "shirt_normal",
    "name": "Normales Hemd (langarm)",
    "slot": "torso",
    "fit": "mid",
    "clo": 0.25,
    "waterproof": false,
    "windproof": false,
    "coverage": "full",
    "upf": 25
  },
  {
    "id": "shirt_flannel",
    "name": "Flanellhemd (langarm)",
    "slot": "torso",
    "fit": "mid",
    "clo": 0.30,
    "waterproof": false,
    "windproof": false,
    "coverage": "full",
    "upf": 30
  },
  {
    "id": "turtleneck_blouse",
    "name": "Rollkragenbluse (langarm)",
    "slot": "torso",
    "fit": "mid",
    "clo": 0.34,
    "waterproof": false,
    "windproof": false,
    "coverage": "full",
    "upf": 30
  },
  {
    "id": "vest_sleeveless",
    "name": "Aermellose Weste",
    "slot": "torso",
    "fit": "mid",
    "clo": 0.12,
    "waterproof": false,
    "windproof": false,
    "coverage": "low",
    "upf": 20
  },
  {
    "id": "sweater_thin",
    "name": "Duenner Pullover",
    "slot": "torso",
    "fit": "mid",
    "clo": 0.20,
    "waterproof": false,
    "windproof": false,
    "coverage": "full",
    "upf": 25
  },
  {
    "id": "sweater_turtleneck_thin",
    "name": "Duenner Rollkragenpullover",
    "slot": "torso",
    "fit": "mid",
    "clo": 0.26,
    "waterproof": false,
    "windproof": false,
    "coverage": "full",
    "upf": 30
  },
  {
    "id": "sweater_thick",
    "name": "Dicker Pullover",
    "slot": "torso",
    "fit": "mid",
    "clo": 0.35,
    "waterproof": false,
    "windproof": false,
    "coverage": "full",
    "upf": 35
  },
  {
    "id": "sweater_turtleneck_thick",
    "name": "Dicker Rollkragenpullover",
    "slot": "torso",
    "fit": "mid",
    "clo": 0.37,
    "waterproof": false,
    "windproof": false,
    "coverage": "full",
    "upf": 35
  },
  {
    "id": "fleece_thin",
    "name": "Fleece-Jacke (duenn)",
    "slot": "torso",
    "fit": "mid",
    "clo": 0.25,
    "waterproof": false,
    "windproof": false,
    "coverage": "full",
    "upf": 30
  },
  {
    "id": "fleece_thick",
    "name": "Fleece-Jacke (dick)",
    "slot": "torso",
    "fit": "mid",
    "clo": 0.30,
    "waterproof": false,
    "windproof": false,
    "coverage": "full",
    "upf": 35
  },
  {
    "id": "vest_insulated",
    "name": "Weste (isoliert)",
    "slot": "torso",
    "fit": "mid",
    "clo": 0.13,
    "waterproof": false,
    "windproof": false,
    "coverage": "low",
    "upf": 30
  },
  {
    "id": "jacket_summer",
    "name": "Leichte Sommerjacke",
    "slot": "torso",
    "fit": "outer",
    "clo": 0.25,
    "waterproof": false,
    "windproof": true,
    "coverage": "full",
    "upf": 30
  },
  {
    "id": "jacket_normal",
    "name": "Jacke",
    "slot": "torso",
    "fit": "outer",
    "clo": 0.35,
    "waterproof": false,
    "windproof": true,
    "coverage": "full",
    "upf": 40
  },
  {
    "id": "softshell",
    "name": "Softshell-Jacke",
    "slot": "torso",
    "fit": "outer",
    "clo": 0.30,
    "waterproof": false,
    "windproof": true,
    "coverage": "full",
    "upf": 40
  },
  {
    "id": "hardshell",
    "name": "Hardshell / Regenjacke",
    "slot": "torso",
    "fit": "outer",
    "clo": 0.10,
    "waterproof": true,
    "windproof": true,
    "coverage": "full",
    "upf": 50
  },
  {
    "id": "windbreaker",
    "name": "Windbreaker",
    "slot": "torso",
    "fit": "outer",
    "clo": 0.08,
    "waterproof": false,
    "windproof": true,
    "coverage": "full",
    "upf": 40
  },
  {
    "id": "down_jacket",
    "name": "Daunenjacke",
    "slot": "torso",
    "fit": "outer",
    "clo": 0.55,
    "waterproof": false,
    "windproof": true,
    "coverage": "full",
    "upf": 50
  },
  {
    "id": "coat",
    "name": "Mantel",
    "slot": "torso",
    "fit": "outer",
    "clo": 0.60,
    "waterproof": false,
    "windproof": true,
    "coverage": "full",
    "upf": 50
  },
  {
    "id": "parka",
    "name": "Parka",
    "slot": "torso",
    "fit": "outer",
    "clo": 0.70,
    "waterproof": true,
    "windproof": true,
    "coverage": "full",
    "upf": 50
  },
  {
    "id": "extreme_cold_jacket",
    "name": "Kuehlhaus-/Gefrierschutzjacke",
    "slot": "torso",
    "fit": "outer",
    "clo": 2.59,
    "waterproof": true,
    "windproof": true,
    "coverage": "full",
    "upf": 50
  },
  {
    "id": "shorts",
    "name": "Shorts",
    "slot": "legs",
    "fit": "mid",
    "clo": 0.06,
    "waterproof": false,
    "windproof": false,
    "coverage": "low",
    "upf": 15
  },
  {
    "id": "hiking_shorts",
    "name": "Kurze Wanderhose",
    "slot": "legs",
    "fit": "mid",
    "clo": 0.11,
    "waterproof": false,
    "windproof": false,
    "coverage": "low",
    "upf": 30
  },
  {
    "id": "pants_light",
    "name": "Leichte Hose",
    "slot": "legs",
    "fit": "mid",
    "clo": 0.20,
    "waterproof": false,
    "windproof": false,
    "coverage": "full",
    "upf": 30
  },
  {
    "id": "pants_standard",
    "name": "Normale Hose",
    "slot": "legs",
    "fit": "mid",
    "clo": 0.25,
    "waterproof": false,
    "windproof": false,
    "coverage": "full",
    "upf": 35
  },
  {
    "id": "pants_flannel",
    "name": "Flanellhose",
    "slot": "legs",
    "fit": "mid",
    "clo": 0.28,
    "waterproof": false,
    "windproof": false,
    "coverage": "full",
    "upf": 35
  },
  {
    "id": "jeans",
    "name": "Jeans",
    "slot": "legs",
    "fit": "mid",
    "clo": 0.25,
    "waterproof": false,
    "windproof": false,
    "coverage": "full",
    "upf": 40
  },
  {
    "id": "joggers_light",
    "name": "Jogginghose (duenn)",
    "slot": "legs",
    "fit": "mid",
    "clo": 0.25,
    "waterproof": false,
    "windproof": false,
    "coverage": "full",
    "upf": 25
  },
  {
    "id": "joggers_heavy",
    "name": "Jogginghose (dick)",
    "slot": "legs",
    "fit": "mid",
    "clo": 0.30,
    "waterproof": false,
    "windproof": false,
    "coverage": "full",
    "upf": 30
  },
  {
    "id": "riding_pants",
    "name": "Reithose",
    "slot": "legs",
    "fit": "mid",
    "clo": 0.15,
    "waterproof": false,
    "windproof": false,
    "coverage": "full",
    "upf": 30
  },
  {
    "id": "rain_pants",
    "name": "Regenhose",
    "slot": "legs",
    "fit": "outer",
    "clo": 0.05,
    "waterproof": true,
    "windproof": true,
    "coverage": "full",
    "upf": 50
  },
  {
    "id": "ski_pants",
    "name": "Skihose",
    "slot": "legs",
    "fit": "outer",
    "clo": 0.35,
    "waterproof": true,
    "windproof": true,
    "coverage": "full",
    "upf": 50
  },
  {
    "id": "skirt_short_light",
    "name": "Leichter Rock (kurz)",
    "slot": "legs",
    "fit": "mid",
    "clo": 0.10,
    "waterproof": false,
    "windproof": false,
    "coverage": "low",
    "upf": 15
  },
  {
    "id": "skirt_midi_light",
    "name": "Leichter Rock (knielang)",
    "slot": "legs",
    "fit": "mid",
    "clo": 0.18,
    "waterproof": false,
    "windproof": false,
    "coverage": "medium",
    "upf": 20
  },
  {
    "id": "skirt_heavy",
    "name": "Schwerer Rock (knielang)",
    "slot": "legs",
    "fit": "mid",
    "clo": 0.25,
    "waterproof": false,
    "windproof": false,
    "coverage": "medium",
    "upf": 30
  },
  {
    "id": "socks_thin",
    "name": "Socken (duenn)",
    "slot": "feet",
    "fit": "base",
    "clo": 0.02,
    "waterproof": false,
    "windproof": false,
    "coverage": "low",
    "upf": 5
  },
  {
    "id": "socks_standard",
    "name": "Socken (normal)",
    "slot": "feet",
    "fit": "base",
    "clo": 0.03,
    "waterproof": false,
    "windproof": false,
    "coverage": "low",
    "upf": 10
  },
  {
    "id": "socks_ankle_thick",
    "name": "Dicke Knoechelsocken",
    "slot": "feet",
    "fit": "base",
    "clo": 0.05,
    "waterproof": false,
    "windproof": false,
    "coverage": "low",
    "upf": 15
  },
  {
    "id": "socks_long_thick",
    "name": "Dicke lange Socken",
    "slot": "feet",
    "fit": "base",
    "clo": 0.10,
    "waterproof": false,
    "windproof": false,
    "coverage": "medium",
    "upf": 20
  },
  {
    "id": "socks_wool",
    "name": "Wollsocken",
    "slot": "feet",
    "fit": "base",
    "clo": 0.08,
    "waterproof": false,
    "windproof": false,
    "coverage": "medium",
    "upf": 20
  },
  {
    "id": "sandals",
    "name": "Sandalen",
    "slot": "feet",
    "fit": "mid",
    "clo": 0.02,
    "waterproof": false,
    "windproof": false,
    "coverage": "low",
    "upf": 0
  },
  {
    "id": "shoes_thin_sole",
    "name": "Schuhe (duenne Sohle)",
    "slot": "feet",
    "fit": "mid",
    "clo": 0.02,
    "waterproof": false,
    "windproof": false,
    "coverage": "medium",
    "upf": 30
  },
  {
    "id": "shoes_thick_sole",
    "name": "Schuhe (dicke Sohle)",
    "slot": "feet",
    "fit": "mid",
    "clo": 0.04,
    "waterproof": false,
    "windproof": false,
    "coverage": "medium",
    "upf": 35
  },
  {
    "id": "sneakers",
    "name": "Sneakers",
    "slot": "feet",
    "fit": "mid",
    "clo": 0.03,
    "waterproof": false,
    "windproof": false,
    "coverage": "medium",
    "upf": 30
  },
  {
    "id": "boots",
    "name": "Stiefel",
    "slot": "feet",
    "fit": "mid",
    "clo": 0.05,
    "waterproof": false,
    "windproof": true,
    "coverage": "full",
    "upf": 50
  },
  {
    "id": "hiking_boots",
    "name": "Wanderstiefel",
    "slot": "feet",
    "fit": "mid",
    "clo": 0.08,
    "waterproof": true,
    "windproof": true,
    "coverage": "full",
    "upf": 50
  },
  {
    "id": "winter_boots",
    "name": "Winterstiefel",
    "slot": "feet",
    "fit": "mid",
    "clo": 0.15,
    "waterproof": true,
    "windproof": true,
    "coverage": "full",
    "upf": 50
  },
  {
    "id": "slippers_fleece",
    "name": "Fleece-Hausschuhe",
    "slot": "feet",
    "fit": "mid",
    "clo": 0.03,
    "waterproof": false,
    "windproof": false,
    "coverage": "medium",
    "upf": 20
  },
  {
    "id": "gaiters",
    "name": "Gamaschen",
    "slot": "feet",
    "fit": "outer",
    "clo": 0.02,
    "waterproof": true,
    "windproof": true,
    "coverage": "full",
    "upf": 50
  },
  {
    "id": "cap_thin",
    "name": "Baseballcap (duenn)",
    "slot": "head",
    "fit": "base",
    "clo": 0.01,
    "waterproof": false,
    "windproof": false,
    "coverage": "low",
    "upf": 25
  },
  {
    "id": "cap_thick",
    "name": "Baseballcap (dick)",
    "slot": "head",
    "fit": "base",
    "clo": 0.02,
    "waterproof": false,
    "windproof": false,
    "coverage": "low",
    "upf": 30
  },
  {
    "id": "sun_hat",
    "name": "Sonnenhut",
    "slot": "head",
    "fit": "base",
    "clo": 0.02,
    "waterproof": false,
    "windproof": false,
    "coverage": "medium",
    "upf": 50
  },
  {
    "id": "straw_hat",
    "name": "Strohhut",
    "slot": "head",
    "fit": "base",
    "clo": 0.02,
    "waterproof": false,
    "windproof": false,
    "coverage": "medium",
    "upf": 30
  },
  {
    "id": "bandana",
    "name": "Bandana / Kopftuch",
    "slot": "head",
    "fit": "base",
    "clo": 0.01,
    "waterproof": false,
    "windproof": false,
    "coverage": "low",
    "upf": 15
  },
  {
    "id": "headband",
    "name": "Stirnband",
    "slot": "head",
    "fit": "base",
    "clo": 0.01,
    "waterproof": false,
    "windproof": false,
    "coverage": "low",
    "upf": 15
  },
  {
    "id": "beanie_light",
    "name": "Leichte Strickmuetze / Beanie",
    "slot": "head",
    "fit": "base",
    "clo": 0.03,
    "waterproof": false,
    "windproof": false,
    "coverage": "medium",
    "upf": 20
  },
  {
    "id": "beanie_thin",
    "name": "Strickmuetze (duenn)",
    "slot": "head",
    "fit": "base",
    "clo": 0.06,
    "waterproof": false,
    "windproof": false,
    "coverage": "medium",
    "upf": 25
  },
  {
    "id": "beanie_thick",
    "name": "Strickmuetze (dick)",
    "slot": "head",
    "fit": "base",
    "clo": 0.10,
    "waterproof": false,
    "windproof": false,
    "coverage": "medium",
    "upf": 30
  },
  {
    "id": "wool_hat_thin",
    "name": "Wollmuetze (duenn)",
    "slot": "head",
    "fit": "base",
    "clo": 0.05,
    "waterproof": false,
    "windproof": false,
    "coverage": "medium",
    "upf": 25
  },
  {
    "id": "wool_hat_thick",
    "name": "Wollmuetze (dick)",
    "slot": "head",
    "fit": "base",
    "clo": 0.08,
    "waterproof": false,
    "windproof": false,
    "coverage": "medium",
    "upf": 30
  },
  {
    "id": "fleece_hat_thin",
    "name": "Fleece-Muetze (duenn)",
    "slot": "head",
    "fit": "base",
    "clo": 0.05,
    "waterproof": false,
    "windproof": false,
    "coverage": "medium",
    "upf": 25
  },
  {
    "id": "fleece_hat_thick",
    "name": "Fleece-Muetze (dick)",
    "slot": "head",
    "fit": "base",
    "clo": 0.08,
    "waterproof": false,
    "windproof": false,
    "coverage": "medium",
    "upf": 30
  },
  {
    "id": "hat_fleece_lined",
    "name": "Muetze mit Fleece-Futter",
    "slot": "head",
    "fit": "base",
    "clo": 0.10,
    "waterproof": false,
    "windproof": true,
    "coverage": "medium",
    "upf": 35
  },
  {
    "id": "wool_hat_earflaps",
    "name": "Wollmuetze mit Ohrenklappen",
    "slot": "head",
    "fit": "base",
    "clo": 0.12,
    "waterproof": false,
    "windproof": true,
    "coverage": "full",
    "upf": 35
  },
  {
    "id": "thinsulate_hat",
    "name": "Thinsulate-Muetze",
    "slot": "head",
    "fit": "base",
    "clo": 0.10,
    "waterproof": false,
    "windproof": true,
    "coverage": "medium",
    "upf": 40
  },
  {
    "id": "fur_hat",
    "name": "Pelzmuetze / Uschanka",
    "slot": "head",
    "fit": "base",
    "clo": 0.15,
    "waterproof": false,
    "windproof": true,
    "coverage": "full",
    "upf": 50
  },
  {
    "id": "trapper_hat",
    "name": "Trappermuetze mit Fell",
    "slot": "head",
    "fit": "base",
    "clo": 0.18,
    "waterproof": false,
    "windproof": true,
    "coverage": "full",
    "upf": 50
  },
  {
    "id": "balaclava_ultralight",
    "name": "Balaclava / Sturmhaube (ultraleicht)",
    "slot": "head",
    "fit": "base",
    "clo": 0.05,
    "waterproof": false,
    "windproof": false,
    "coverage": "full",
    "upf": 30
  },
  {
    "id": "balaclava_thin",
    "name": "Balaclava (duenn)",
    "slot": "head",
    "fit": "base",
    "clo": 0.07,
    "waterproof": false,
    "windproof": true,
    "coverage": "full",
    "upf": 35
  },
  {
    "id": "balaclava_fleece",
    "name": "Balaclava (Fleece)",
    "slot": "head",
    "fit": "base",
    "clo": 0.10,
    "waterproof": false,
    "windproof": true,
    "coverage": "full",
    "upf": 40
  },
  {
    "id": "helmet_liner",
    "name": "Helm-Unterziehmuetze",
    "slot": "head",
    "fit": "base",
    "clo": 0.03,
    "waterproof": false,
    "windproof": false,
    "coverage": "medium",
    "upf": 20
  },
  {
    "id": "cotton_scarf_thin",
    "name": "Baumwollhalstuch (duenn)",
    "slot": "neck",
    "fit": "base",
    "clo": 0.05,
    "waterproof": false,
    "windproof": false,
    "coverage": "low",
    "upf": 15
  },
  {
    "id": "cotton_scarf_thick",
    "name": "Baumwollhalstuch (dick)",
    "slot": "neck",
    "fit": "base",
    "clo": 0.08,
    "waterproof": false,
    "windproof": false,
    "coverage": "medium",
    "upf": 20
  },
  {
    "id": "buff_merino",
    "name": "Buff / Schlauchschal (Merino)",
    "slot": "neck",
    "fit": "base",
    "clo": 0.10,
    "waterproof": false,
    "windproof": false,
    "coverage": "medium",
    "upf": 25
  },
  {
    "id": "wool_scarf_thin",
    "name": "Wollschal (duenn)",
    "slot": "neck",
    "fit": "base",
    "clo": 0.20,
    "waterproof": false,
    "windproof": true,
    "coverage": "full",
    "upf": 35
  },
  {
    "id": "wool_scarf_thick",
    "name": "Wollschal (dick)",
    "slot": "neck",
    "fit": "base",
    "clo": 0.30,
    "waterproof": false,
    "windproof": true,
    "coverage": "full",
    "upf": 40
  },
  {
    "id": "cashmere_scarf",
    "name": "Kaschmirschal",
    "slot": "neck",
    "fit": "base",
    "clo": 0.30,
    "waterproof": false,
    "windproof": true,
    "coverage": "full",
    "upf": 40
  },
  {
    "id": "neck_gaiter",
    "name": "Halsgamasche / Neck Gaiter",
    "slot": "neck",
    "fit": "base",
    "clo": 0.08,
    "waterproof": false,
    "windproof": true,
    "coverage": "medium",
    "upf": 30
  },
  {
    "id": "liner_gloves_thin",
    "name": "Liner-Handschuhe (duenn)",
    "slot": "hands",
    "fit": "base",
    "clo": 0.10,
    "waterproof": false,
    "windproof": false,
    "coverage": "full",
    "upf": 20
  },
  {
    "id": "liner_gloves_thick",
    "name": "Liner-Handschuhe (dick)",
    "slot": "hands",
    "fit": "base",
    "clo": 0.15,
    "waterproof": false,
    "windproof": false,
    "coverage": "full",
    "upf": 25
  },
  {
    "id": "fleece_gloves_thin",
    "name": "Fleece-Handschuhe (duenn)",
    "slot": "hands",
    "fit": "mid",
    "clo": 0.20,
    "waterproof": false,
    "windproof": false,
    "coverage": "full",
    "upf": 30
  },
  {
    "id": "fleece_gloves_thick",
    "name": "Fleece-Handschuhe (dick)",
    "slot": "hands",
    "fit": "mid",
    "clo": 0.35,
    "waterproof": false,
    "windproof": false,
    "coverage": "full",
    "upf": 35
  },
  {
    "id": "leather_gloves",
    "name": "Lederhandschuhe",
    "slot": "hands",
    "fit": "mid",
    "clo": 0.25,
    "waterproof": false,
    "windproof": true,
    "coverage": "full",
    "upf": 50
  },
  {
    "id": "ski_gloves_thin",
    "name": "Skihandschuhe (duenn)",
    "slot": "hands",
    "fit": "outer",
    "clo": 0.40,
    "waterproof": true,
    "windproof": true,
    "coverage": "full",
    "upf": 50
  },
  {
    "id": "ski_gloves_thick",
    "name": "Skihandschuhe (dick)",
    "slot": "hands",
    "fit": "outer",
    "clo": 0.60,
    "waterproof": true,
    "windproof": true,
    "coverage": "full",
    "upf": 50
  },
  {
    "id": "umbrella",
    "name": "Regenschirm",
    "slot": "hands",
    "fit": "outer",
    "clo": 0.0,
    "waterproof": true,
    "windproof": false,
    "coverage": "full",
    "upf": 50
  },
  {
    "id": "down_mittens",
    "name": "Daunenfaeustlinge (Expedition)",
    "slot": "hands",
    "fit": "outer",
    "clo": 1.00,
    "waterproof": true,
    "windproof": true,
    "coverage": "full",
    "upf": 50
  }
]
